polyspark/__init__.py
polyspark/cli.py
polyspark/exceptions.py
polyspark/factory.py
polyspark/handlers.py
polyspark/io.py
polyspark/protocols.py
polyspark/schema.py
polyspark/testing.py
polyspark-0.5.0.dist-info/METADATA
polyspark-0.5.0.dist-info/WHEEL
polyspark-0.5.0.dist-info/entry_points.txt
polyspark-0.5.0.dist-info/licenses/LICENSE
polyspark-0.5.0.dist-info/RECORD
