Metadata-Version: 2.4
Name: polyspark
Version: 0.5.0
Summary: Generate PySpark DataFrames using polyfactory for testing and development
Project-URL: Homepage, https://github.com/odosmatthews/polyspark
Project-URL: Documentation, https://github.com/odosmatthews/polyspark#readme
Project-URL: Repository, https://github.com/odosmatthews/polyspark
Project-URL: Issues, https://github.com/odosmatthews/polyspark/issues
Author-email: Odos Matthews <odosmatthews@gmail.com>
License-Expression: MIT
License-File: LICENSE
Keywords: dataframe,factory,mock-data,polyfactory,pyspark,testing
Classifier: Development Status :: 4 - Beta
Classifier: Intended Audience :: Developers
Classifier: License :: OSI Approved :: MIT License
Classifier: Programming Language :: Python :: 3
Classifier: Programming Language :: Python :: 3.8
Classifier: Programming Language :: Python :: 3.9
Classifier: Programming Language :: Python :: 3.10
Classifier: Programming Language :: Python :: 3.11
Classifier: Programming Language :: Python :: 3.12
Classifier: Topic :: Software Development :: Libraries :: Python Modules
Classifier: Topic :: Software Development :: Testing
Requires-Python: >=3.8
Requires-Dist: polyfactory>=2.0.0
Requires-Dist: typing-extensions>=4.0.0
Provides-Extra: dev
Requires-Dist: black>=23.0.0; extra == 'dev'
Requires-Dist: mypy>=1.0.0; extra == 'dev'
Requires-Dist: pydantic>=2.0.0; extra == 'dev'
Requires-Dist: pyspark>=3.0.0; extra == 'dev'
Requires-Dist: pytest-cov>=4.0.0; extra == 'dev'
Requires-Dist: pytest>=7.0.0; extra == 'dev'
Requires-Dist: ruff>=0.1.0; extra == 'dev'
